torchact/__init__.py
torchact/functional/__init__.py
torchact/functional/func.py
torchact/nn/__init__.py
torchact/nn/ab_relu.py
torchact/nn/elu.py
torchact/nn/leaky_relu.py
torchact/nn/log_sigmoid.py
torchact/nn/log_softmax.py
torchact/nn/relu.py
torchact/nn/sigmoid.py
torchact/nn/sinlu.py
torchact/nn/softmax.py
torchact/nn/step.py
torchact-1.1.2.dist-info/LICENSE
torchact-1.1.2.dist-info/METADATA
torchact-1.1.2.dist-info/WHEEL
torchact-1.1.2.dist-info/top_level.txt
torchact-1.1.2.dist-info/RECORD
